{"data":[{"id":100295001,"name":"Brave Beauty of Ruby Regard - Bradamante","type":"Tuner Monster","desc":"(This card is always treated as an \"Infernoble Knight\" card.)\r\nYou can discard this card, then target 1 Warrior monster you control; equip it with 1 appropriate Equip Spell from your Deck. When this card that is not equipped with any Equip Card is destroyed by battle with an opponent's monster and sent to the GY: You can Special Summon this card, and if you do, equip that monster your opponent controls to this card. You can only use each effect of \"Brave Beauty of Ruby Regard - Bradamante\" once per turn.","atk":500,"def":200,"level":1,"race":"Warrior","attribute":"FIRE","card_sets":null,"card_images":[{"id":100295001,"image_url":"https://images.ygoprodeck.com/images/cards/100295001.jpg","image_url_small":"https://images.ygoprodeck.com/images/cards_small/100295001.jpg"}],"card_prices":[{"cardmarket_price":"0.00","tcgplayer_price":"0.00","ebay_price":"0.00","amazon_price":"0.00","coolstuffinc_price":"0.00"}]}]}