{"data":[{"id":15052462,"name":"Violet Crystal","type":"Spell Card","desc":"(This card is not treated as a \"Crystal\" card.)\r\nEquip only to a Zombie monster. It gains 300 ATK/DEF.","atk":0,"def":0,"level":0,"race":"Equip","attribute":null,"card_sets":[{"set_name":"Legend of Blue Eyes White Dragon","set_code":"LOB-042","set_rarity":"Short Print","set_rarity_code":"(SP)","set_price":"4.98"},{"set_name":"Legend of Blue Eyes White Dragon","set_code":"LOB-E033","set_rarity":"Short Print","set_rarity_code":"(SP)","set_price":"9.71"},{"set_name":"Legend of Blue Eyes White Dragon","set_code":"LOB-EN042","set_rarity":"Short Print","set_rarity_code":"(SP)","set_price":"56.48"},{"set_name":"Speed Duel: Arena of Lost Souls","set_code":"SBLS-EN035","set_rarity":"Common","set_rarity_code":"(C)","set_price":"1.03"}],"card_images":[{"id":15052462,"image_url":"https://images.ygoprodeck.com/images/cards/15052462.jpg","image_url_small":"https://images.ygoprodeck.com/images/cards_small/15052462.jpg"}],"card_prices":[{"cardmarket_price":"0.03","tcgplayer_price":"0.14","ebay_price":"12.71","amazon_price":"0.25","coolstuffinc_price":"0.25"}]}]}