{"data":[{"id":16960351,"name":"Dracocension","type":"Spell Card","desc":"Once per turn: You can Tribute 1 Dragon-Type monster that has a Level; Special Summon, from your Deck, 1 Wyrm-Type monster with the same Level as the Tributed monster's original Level, and if you do, any monster destroyed by battle with that monster is shuffled into the Deck instead of going to the Graveyard.","atk":0,"def":0,"level":0,"race":"Continuous","attribute":null,"card_sets":[{"set_name":"Duelist Alliance","set_code":"DUEA-EN064","set_rarity":"Common","set_rarity_code":"(C)","set_price":"1.29"}],"card_images":[{"id":16960351,"image_url":"https://images.ygoprodeck.com/images/cards/16960351.jpg","image_url_small":"https://images.ygoprodeck.com/images/cards_small/16960351.jpg"}],"card_prices":[{"cardmarket_price":"0.05","tcgplayer_price":"0.10","ebay_price":"0.99","amazon_price":"0.25","coolstuffinc_price":"0.49"}]}]}