{"data":[{"id":17722185,"name":"Invincibility Barrier","type":"Trap Card","desc":"Once per turn: You can banish 1 face-up Ritual, Fusion, Synchro, Xyz, Pendulum, or Link Monster you control; this turn, the effects of monsters with the same card type as that banished monster (Ritual, Fusion, Synchro, Xyz, Pendulum, or Link) are negated.","atk":0,"def":0,"level":0,"race":"Continuous","attribute":null,"card_sets":[{"set_name":"2019 Gold Sarcophagus Tin Mega Pack","set_code":"MP19-EN211","set_rarity":"Common","set_rarity_code":"(C)","set_price":"1.02"},{"set_name":"Soul Fusion","set_code":"SOFU-EN076","set_rarity":"Common","set_rarity_code":"(C)","set_price":"1.03"}],"card_images":[{"id":17722185,"image_url":"https://images.ygoprodeck.com/images/cards/17722185.jpg","image_url_small":"https://images.ygoprodeck.com/images/cards_small/17722185.jpg"}],"card_prices":[{"cardmarket_price":"0.03","tcgplayer_price":"0.01","ebay_price":"1.09","amazon_price":"0.20","coolstuffinc_price":"0.49"}]}]}