{"data":[{"id":23002292,"name":"Red Reboot","type":"Trap Card","desc":"When your opponent activates a Trap Card: Negate the activation, and if you do, Set that card face-down, then they can Set 1 other Trap directly from their Deck. For the rest of this turn after this card resolves, your opponent cannot activate Trap Cards. You can activate this card from your hand by paying half your LP.","atk":0,"def":0,"level":0,"race":"Counter","attribute":null,"card_sets":[{"set_name":"2019 Gold Sarcophagus Tin Mega Pack","set_code":"MP19-EN046","set_rarity":"Prismatic Secret Rare","set_rarity_code":"(PScR)","set_price":"4.28"},{"set_name":"Duel Devastator","set_code":"DUDE-EN056","set_rarity":"Ultra Rare","set_rarity_code":"(UR)","set_price":"2.13"},{"set_name":"Flames of Destruction","set_code":"FLOD-EN068","set_rarity":"Super Rare","set_rarity_code":"(SR)","set_price":"1.72"},{"set_name":"OTS Tournament Pack 19","set_code":"OP19-EN027","set_rarity":"Common","set_rarity_code":"(C)","set_price":"1.17"},{"set_name":"OTS Tournament Pack 19 (POR)","set_code":"OP19-PT027","set_rarity":"Common","set_rarity_code":"(C)","set_price":"0"},{"set_name":"Structure Deck: Rokket Revolt","set_code":"SDRR-EN035","set_rarity":"Common","set_rarity_code":"(C)","set_price":"1.45"}],"card_images":[{"id":23002292,"image_url":"https://images.ygoprodeck.com/images/cards/23002292.jpg","image_url_small":"https://images.ygoprodeck.com/images/cards_small/23002292.jpg"}],"card_prices":[{"cardmarket_price":"0.05","tcgplayer_price":"0.21","ebay_price":"5.95","amazon_price":"1.03","coolstuffinc_price":"0.49"}]}]}