{"data":[{"id":23912837,"name":"Resh Shaddoll Incarnation","type":"Trap Card","desc":"Target 1 \"Shaddoll\" monster in your GY; Special Summon it in face-up or face-down Defense Position.\r\nYou can banish this card and 1 \"Shaddoll\" card from your GY, then activate 1 of these effects;\r\n● Change 1 face-down monster you control to face-up Defense Position.\r\n● Change 1 face-up monster you control to face-down Defense Position.\r\nYou can only use 1 \"Resh Shaddoll Incarnation\" effect per turn, and only once that turn.","atk":0,"def":0,"level":0,"race":"Normal","attribute":null,"card_sets":[{"set_name":"Structure Deck: Shaddoll Showdown","set_code":"SDSH-EN033","set_rarity":"Super Rare","set_rarity_code":"(SR)","set_price":"1.27"}],"card_images":[{"id":23912837,"image_url":"https://images.ygoprodeck.com/images/cards/23912837.jpg","image_url_small":"https://images.ygoprodeck.com/images/cards_small/23912837.jpg"}],"card_prices":[{"cardmarket_price":"0.24","tcgplayer_price":"0.47","ebay_price":"2.95","amazon_price":"0.91","coolstuffinc_price":"0.99"}]}]}