{"data":[{"id":24673894,"name":"Changing Destiny","type":"Trap Card","desc":"When an opponent's monster declares an attack: Target the attacking monster; negate the attack, and if you do, change it to Defense Position and it cannot change its battle position while it is face-up on the field. Then, your opponent chooses 1 of these effects.\n● You (the opponent of this card's activator) gain LP equal to half the target's ATK.\n● Your opponent (the activator of this card) takes damage equal to half the target's ATK.","atk":0,"def":0,"level":0,"race":"Normal","attribute":null,"card_sets":[{"set_name":"Absolute Powerforce","set_code":"ABPF-EN063","set_rarity":"Common","set_rarity_code":"(C)","set_price":"1.06"},{"set_name":"Battle Pack: Epic Dawn","set_code":"BP01-EN104","set_rarity":"Common","set_rarity_code":"(C)","set_price":"1.2"},{"set_name":"Battle Pack: Epic Dawn","set_code":"BP01-EN104","set_rarity":"Starfoil Rare","set_rarity_code":"(SFR)","set_price":"1.2"},{"set_name":"Legendary Collection 5D's Mega Pack","set_code":"LC5D-EN081","set_rarity":"Common","set_rarity_code":"(C)","set_price":"1.18"}],"card_images":[{"id":24673894,"image_url":"https://images.ygoprodeck.com/images/cards/24673894.jpg","image_url_small":"https://images.ygoprodeck.com/images/cards_small/24673894.jpg"}],"card_prices":[{"cardmarket_price":"0.09","tcgplayer_price":"0.19","ebay_price":"0.99","amazon_price":"1.02","coolstuffinc_price":"0.25"}]}]}