{"data":[{"id":28062325,"name":"Bamboo Scrap","type":"Trap Card","desc":"Tribute 1 Plant-Type monster. Special Summon 2 \"Plant Tokens\" (Plant-Type/EARTH/Level 1/ATK 800/DEF 500) to your opponent's side of the field in Defense Position.","atk":0,"def":0,"level":0,"race":"Normal","attribute":null,"card_sets":[{"set_name":"Crossroads of Chaos","set_code":"CSOC-EN075","set_rarity":"Common","set_rarity_code":"(C)","set_price":"1.05"}],"card_images":[{"id":28062325,"image_url":"https://images.ygoprodeck.com/images/cards/28062325.jpg","image_url_small":"https://images.ygoprodeck.com/images/cards_small/28062325.jpg"}],"card_prices":[{"cardmarket_price":"0.04","tcgplayer_price":"0.19","ebay_price":"0.99","amazon_price":"0.20","coolstuffinc_price":"0.25"}]}]}