{"data":[{"id":2980764,"name":"Consecrated Light","type":"Effect Monster","desc":"Neither player can Normal or Special Summon DARK monsters or declare an attack with a DARK monster. This card cannot be destroyed by battle with a DARK monster, also you take no battle damage from that battle.","atk":0,"def":0,"level":1,"race":"Fairy","attribute":"LIGHT","card_sets":[{"set_name":"Absolute Powerforce","set_code":"ABPF-EN033","set_rarity":"Short Print","set_rarity_code":"(SP)","set_price":"1.82"},{"set_name":"Astral Pack Four","set_code":"AP04-EN006","set_rarity":"Super Rare","set_rarity_code":"(SR)","set_price":"6.22"},{"set_name":"Lost Sanctuary Structure Deck","set_code":"SDLS-EN022","set_rarity":"Common","set_rarity_code":"(C)","set_price":"1.23"}],"card_images":[{"id":2980764,"image_url":"https://images.ygoprodeck.com/images/cards/2980764.jpg","image_url_small":"https://images.ygoprodeck.com/images/cards_small/2980764.jpg"}],"card_prices":[{"cardmarket_price":"0.21","tcgplayer_price":"0.47","ebay_price":"1.99","amazon_price":"4.40","coolstuffinc_price":"0.99"}]}]}