{"data":[{"id":3026686,"name":"Valkyrie Dritte","type":"Effect Monster","desc":"If this card is Normal or Special Summoned: You can add 1 \"Valkyrie\" card from your Deck to your hand, except \"Valkyrie Dritte\". You can only use this effect of \"Valkyrie Dritte\" once per turn. Gains 200 ATK for each of your opponent's banished monsters.","atk":1000,"def":1600,"level":4,"race":"Fairy","attribute":"LIGHT","card_sets":[{"set_name":"Shadows in Valhalla","set_code":"SHVA-EN001","set_rarity":"Super Rare","set_rarity_code":"(SR)","set_price":"1.46"}],"card_images":[{"id":3026686,"image_url":"https://images.ygoprodeck.com/images/cards/3026686.jpg","image_url_small":"https://images.ygoprodeck.com/images/cards_small/3026686.jpg"}],"card_prices":[{"cardmarket_price":"0.18","tcgplayer_price":"0.39","ebay_price":"1.47","amazon_price":"1.00","coolstuffinc_price":"0.39"}]}]}