{"data":[{"id":31044787,"name":"Ferret Flames","type":"Trap Card","desc":"If the combined ATK of all face-up monsters your opponent controls is higher than your LP: Make your opponent shuffle monsters they control into the Deck (their choice), so that the combined ATK of the remaining monsters they control becomes less than or equal to your LP.","atk":0,"def":0,"level":0,"race":"Normal","attribute":null,"card_sets":[{"set_name":"2016 Mega-Tin Mega Pack","set_code":"MP16-EN093","set_rarity":"Common","set_rarity_code":"(C)","set_price":"3.75"},{"set_name":"Clash of Rebellions","set_code":"CORE-EN077","set_rarity":"Common","set_rarity_code":"(C)","set_price":"4.42"},{"set_name":"Structure Deck: Legend of the Crystal Beasts","set_code":"SDCB-EN039","set_rarity":"Common","set_rarity_code":"(C)","set_price":"0"}],"card_images":[{"id":31044787,"image_url":"https://images.ygoprodeck.com/images/cards/31044787.jpg","image_url_small":"https://images.ygoprodeck.com/images/cards_small/31044787.jpg"}],"card_prices":[{"cardmarket_price":"0.50","tcgplayer_price":"0.15","ebay_price":"3.25","amazon_price":"5.03","coolstuffinc_price":"2.99"}]}]}