{"data":[{"id":39581190,"name":"Subterror Nemesis Archer","type":"Effect Monster","desc":"At the start of the Damage Step, if this card attacks an opponent's face-down Defense Position monster, and you control another \"Subterror\" monster: You can shuffle that opponent's monster into the Deck. If this card on the field is destroyed by battle or card effect and sent to the GY: You can Special Summon 1 \"Subterror\" monster from your Deck in face-up or face-down Defense Position. You can only use each effect of \"Subterror Nemesis Archer\" once per turn.","atk":1600,"def":1400,"level":3,"race":"Fairy","attribute":"EARTH","card_sets":[{"set_name":"Invasion: Vengeance","set_code":"INOV-EN082","set_rarity":"Secret Rare","set_rarity_code":"(ScR)","set_price":"5.97"},{"set_name":"OTS Tournament Pack 11","set_code":"OP11-EN005","set_rarity":"Super Rare","set_rarity_code":"(SR)","set_price":"1.61"},{"set_name":"OTS Tournament Pack 11 (POR)","set_code":"OP11-PT005","set_rarity":"Super Rare","set_rarity_code":"(SR)","set_price":"0.00"}],"card_images":[{"id":39581190,"image_url":"https://images.ygoprodeck.com/images/cards/39581190.jpg","image_url_small":"https://images.ygoprodeck.com/images/cards_small/39581190.jpg"}],"card_prices":[{"cardmarket_price":"0.34","tcgplayer_price":"0.90","ebay_price":"2.95","amazon_price":"8.93","coolstuffinc_price":"0.79"}]}]}