{"data":[{"id":4017398,"name":"Zexal Entrust","type":"Spell Card","desc":"Target 1 \"Utopia\", \"ZW -\", or \"ZS -\" monster in your GY; add it to your hand or Special Summon it. If your opponent's LP are at least 2000 higher than yours, except the turn this card was sent to the GY: You can banish this card from your GY, then target 1 \"Zexal\" Spell/Trap in your GY, except \"Zexal Entrust\"; add it to your hand. You can only use each effect of \"Zexal Entrust\" once per turn.","atk":0,"def":0,"level":0,"race":"Normal","attribute":null,"card_sets":[{"set_name":"2022 Tin of the Pharaoh's Gods","set_code":"MP22-EN092","set_rarity":"Common","set_rarity_code":"(C)","set_price":"0"},{"set_name":"Lightning Overdrive","set_code":"LIOV-EN052","set_rarity":"Common","set_rarity_code":"(C)","set_price":"0.96"}],"card_images":[{"id":4017398,"image_url":"https://images.ygoprodeck.com/images/cards/4017398.jpg","image_url_small":"https://images.ygoprodeck.com/images/cards_small/4017398.jpg"}],"card_prices":[{"cardmarket_price":"0.10","tcgplayer_price":"0.07","ebay_price":"0.99","amazon_price":"49.99","coolstuffinc_price":"0.39"}]}]}