{"data":[{"id":4064256,"name":"Zombie World","type":"Spell Card","desc":"All monsters on the field and in the GYs become Zombie monsters. Neither player can Tribute Summon monsters, except Zombie monsters.","atk":0,"def":0,"level":0,"race":"Field","attribute":null,"card_sets":[{"set_name":"Duel Overload","set_code":"DUOV-EN091","set_rarity":"Ultra Rare","set_rarity_code":"(UR)","set_price":"3.71"},{"set_name":"Duelist League 13 participation cards","set_code":"DL13-EN017","set_rarity":"Rare","set_rarity_code":"(R)","set_price":"25.77"},{"set_name":"Ghosts From the Past: The 2nd Haunting","set_code":"GFP2-EN154","set_rarity":"Ultra Rare","set_rarity_code":"(UR)","set_price":"1.88"},{"set_name":"Legendary Collection 4: Joey's World Mega Pack","set_code":"LCJW-EN213","set_rarity":"Ultra Rare","set_rarity_code":"(UR)","set_price":"4.88"},{"set_name":"OTS Tournament Pack 7","set_code":"OP07-EN019","set_rarity":"Common","set_rarity_code":"(C)","set_price":"2.74"},{"set_name":"OTS Tournament Pack 7 (POR)","set_code":"OP07-PT019","set_rarity":"Common","set_rarity_code":"(C)","set_price":"0.00"},{"set_name":"Structure Deck: Zombie Horde","set_code":"SR07-EN025","set_rarity":"Common","set_rarity_code":"(C)","set_price":"2.66"},{"set_name":"Zombie World Structure Deck","set_code":"SDZW-EN017","set_rarity":"Common","set_rarity_code":"(C)","set_price":"3.11"}],"card_images":[{"id":4064256,"image_url":"https://images.ygoprodeck.com/images/cards/4064256.jpg","image_url_small":"https://images.ygoprodeck.com/images/cards_small/4064256.jpg"}],"card_prices":[{"cardmarket_price":"0.53","tcgplayer_price":"0.79","ebay_price":"1.50","amazon_price":"1.52","coolstuffinc_price":"2.99"}]}]}