{"data":[{"id":473469,"name":"Driving Snow","type":"Trap Card","desc":"You can only activate this card when 1 or more of your Trap Cards are destroyed and sent from the field to the Graveyard by a card effect your opponent controls. Destroy 1 Spell or Trap Card on the field.","atk":0,"def":0,"level":0,"race":"Normal","attribute":null,"card_sets":[{"set_name":"Pharaoh's Servant","set_code":"PSV-018","set_rarity":"Common","set_rarity_code":"(C)","set_price":"1.06"},{"set_name":"Pharaoh's Servant","set_code":"PSV-E018","set_rarity":"Common","set_rarity_code":"(C)","set_price":"8.54"},{"set_name":"Pharaoh's Servant","set_code":"PSV-EN018","set_rarity":"Common","set_rarity_code":"(C)","set_price":"1.75"}],"card_images":[{"id":473469,"image_url":"https://images.ygoprodeck.com/images/cards/473469.jpg","image_url_small":"https://images.ygoprodeck.com/images/cards_small/473469.jpg"}],"card_prices":[{"cardmarket_price":"0.17","tcgplayer_price":"0.12","ebay_price":"0.99","amazon_price":"0.20","coolstuffinc_price":"0.25"}]}]}