{"data":[{"id":48468330,"name":"Terrifying Toddler of Torment","type":"Flip Effect Monster","desc":"FLIP: You can send 1 Fiend monster from your Deck to the GY.\r\nIf this card is sent from the hand or Deck to the GY: You can Special Summon this card in face-down Defense Position. You can only use each effect of \"Terrifying Toddler of Torment\" once per turn.","atk":0,"def":2000,"level":3,"race":"Fiend","attribute":"DARK","card_sets":[{"set_name":"2019 Gold Sarcophagus Tin Mega Pack","set_code":"MP19-EN091","set_rarity":"Common","set_rarity_code":"(C)","set_price":"1.05"},{"set_name":"Cybernetic Horizon","set_code":"CYHO-EN022","set_rarity":"Common","set_rarity_code":"(C)","set_price":"1.01"}],"card_images":[{"id":48468330,"image_url":"https://images.ygoprodeck.com/images/cards/48468330.jpg","image_url_small":"https://images.ygoprodeck.com/images/cards_small/48468330.jpg"}],"card_prices":[{"cardmarket_price":"0.07","tcgplayer_price":"0.09","ebay_price":"0.99","amazon_price":"0.45","coolstuffinc_price":"0.49"}]}]}