{"data":[{"id":49669730,"name":"Water Hazard","type":"Spell Card","desc":"Once per turn: You can Special Summon 1 Level 4 or lower WATER monster from your hand. You must control no monsters to activate and to resolve this effect.","atk":0,"def":0,"level":0,"race":"Continuous","attribute":null,"card_sets":[{"set_name":"Ancient Prophecy","set_code":"ANPR-EN056","set_rarity":"Common","set_rarity_code":"(C)","set_price":"1.61"},{"set_name":"Realm of the Sea Emperor Structure Deck","set_code":"SDRE-EN026","set_rarity":"Common","set_rarity_code":"(C)","set_price":"1.5"},{"set_name":"Speed Duel: Attack from the Deep","set_code":"SBAD-EN033","set_rarity":"Common","set_rarity_code":"(C)","set_price":"1.13"}],"card_images":[{"id":49669730,"image_url":"https://images.ygoprodeck.com/images/cards/49669730.jpg","image_url_small":"https://images.ygoprodeck.com/images/cards_small/49669730.jpg"}],"card_prices":[{"cardmarket_price":"0.12","tcgplayer_price":"0.24","ebay_price":"1.75","amazon_price":"1.30","coolstuffinc_price":"0.25"}]}]}