{"data":[{"id":49888191,"name":"Garnecia Elefantis","type":"Normal Monster","desc":"A monster so heavy that each step rocks the earth.","atk":2400,"def":2000,"level":7,"race":"Beast-Warrior","attribute":"EARTH","card_sets":[{"set_name":"Metal Raiders","set_code":"MRD-125","set_rarity":"Super Rare","set_rarity_code":"(SR)","set_price":"5.44"},{"set_name":"Metal Raiders","set_code":"MRD-E125","set_rarity":"Super Rare","set_rarity_code":"(SR)","set_price":"11.96"},{"set_name":"Metal Raiders","set_code":"MRD-EN125","set_rarity":"Super Rare","set_rarity_code":"(SR)","set_price":"12.36"}],"card_images":[{"id":49888191,"image_url":"https://images.ygoprodeck.com/images/cards/49888191.jpg","image_url_small":"https://images.ygoprodeck.com/images/cards_small/49888191.jpg"}],"card_prices":[{"cardmarket_price":"2.27","tcgplayer_price":"0.95","ebay_price":"2.19","amazon_price":"4.31","coolstuffinc_price":"1.99"}]}]}