{"data":[{"id":52331012,"name":"Tri-Brigade Rugal the Silver Sheller","type":"Link Monster","desc":"2+ Beast, Beast-Warrior, and/or Winged Beast monsters\r\nDuring your opponent's Main Phase (Quick Effect): You can Special Summon 1 Level 4 or lower Beast, Beast-Warrior, or Winged Beast monster from your hand or GY, but negate its effects, also, return it to the hand during the End Phase. If this card is sent to the GY: You can make all monsters your opponent currently controls lose 300 ATK for each Monster Type you control, until the end of this turn. You can only use each effect of \"Tri-Brigade Rugal the Silver Sheller\" once per turn.","atk":2300,"def":0,"level":0,"race":"Beast-Warrior","attribute":"EARTH","card_sets":[{"set_name":"2021 Tin of Ancient Battles","set_code":"MP21-EN197","set_rarity":"Super Rare","set_rarity_code":"(SR)","set_price":"1.04"},{"set_name":"Phantom Rage","set_code":"PHRA-EN047","set_rarity":"Common","set_rarity_code":"(C)","set_price":"0.97"}],"card_images":[{"id":52331012,"image_url":"https://images.ygoprodeck.com/images/cards/52331012.jpg","image_url_small":"https://images.ygoprodeck.com/images/cards_small/52331012.jpg"}],"card_prices":[{"cardmarket_price":"0.07","tcgplayer_price":"0.09","ebay_price":"0.99","amazon_price":"59.99","coolstuffinc_price":"0.25"}]}]}