{"data":[{"id":55573346,"name":"Oops!","type":"Trap Card","desc":"Target 1 card you control; destroy it.","atk":0,"def":0,"level":0,"race":"Normal","attribute":null,"card_sets":[{"set_name":"2018 Mega-Tin Mega Pack","set_code":"MP18-EN223","set_rarity":"Common","set_rarity_code":"(C)","set_price":"1.08"},{"set_name":"Extreme Force","set_code":"EXFO-EN080","set_rarity":"Short Print","set_rarity_code":"(SP)","set_price":"1.04"}],"card_images":[{"id":55573346,"image_url":"https://images.ygoprodeck.com/images/cards/55573346.jpg","image_url_small":"https://images.ygoprodeck.com/images/cards_small/55573346.jpg"}],"card_prices":[{"cardmarket_price":"0.08","tcgplayer_price":"0.11","ebay_price":"0.99","amazon_price":"0.25","coolstuffinc_price":"0.49"}]}]}