{"data":[{"id":58257569,"name":"Red-Eyes Baby Dragon","type":"Effect Monster","desc":"When this card is destroyed by battle and sent to the GY: You can Special Summon 1 Level 7 or lower \"Red-Eyes\" monster from your Deck, and if you do, equip this card from the GY to it. It gains 300 ATK. If this card is sent to the GY while equipped to a monster: You can add 1 Level 1 Dragon monster from your Deck or GY to your hand.","atk":1200,"def":700,"level":3,"race":"Dragon","attribute":"DARK","card_sets":[{"set_name":"Legendary Duelists","set_code":"LEDU-EN001","set_rarity":"Ultra Rare","set_rarity_code":"(UR)","set_price":"17.46"},{"set_name":"Legendary Duelists: Season 1","set_code":"LDS1-EN010","set_rarity":"Secret Rare","set_rarity_code":"(ScR)","set_price":"19.85"}],"card_images":[{"id":58257569,"image_url":"https://images.ygoprodeck.com/images/cards/58257569.jpg","image_url_small":"https://images.ygoprodeck.com/images/cards_small/58257569.jpg"}],"card_prices":[{"cardmarket_price":"12.20","tcgplayer_price":"12.60","ebay_price":"19.99","amazon_price":"20.98","coolstuffinc_price":"13.99"}]}]}