{"data":[{"id":58332301,"name":"Evil HERO Dark Gaia","type":"Fusion Monster","desc":"1 Fiend-Type monster + 1 Rock-Type monster\nMust be Special Summoned with \"Dark Fusion\" and cannot be Special Summoned by other ways. The original ATK of this card is equal to the combined original ATK of the Fusion Material Monsters used to Fusion Summon it. When this card declares an attack: You can change all Defense Position monsters your opponent controls to face-up Attack Position. (Flip Effects are not activated at this time.)","atk":0,"def":0,"level":8,"race":"Fiend","attribute":"EARTH","card_sets":[{"set_name":"Duelist Pack: Jaden Yuki 3","set_code":"DP06-EN010","set_rarity":"Common","set_rarity_code":"(C)","set_price":"2.85"},{"set_name":"Gladiator's Assault","set_code":"GLAS-EN040","set_rarity":"Rare","set_rarity_code":"(R)","set_price":"2.62"},{"set_name":"Legendary Collection 2: The Duel Academy Years Mega Pack","set_code":"LCGX-EN069","set_rarity":"Super Rare","set_rarity_code":"(SR)","set_price":"6.51"},{"set_name":"Legendary Duelists: Season 3","set_code":"LDS3-EN029","set_rarity":"Common","set_rarity_code":"(C)","set_price":"0.93"}],"card_images":[{"id":58332301,"image_url":"https://images.ygoprodeck.com/images/cards/58332301.jpg","image_url_small":"https://images.ygoprodeck.com/images/cards_small/58332301.jpg"}],"card_prices":[{"cardmarket_price":"0.16","tcgplayer_price":"0.18","ebay_price":"1.00","amazon_price":"0.25","coolstuffinc_price":"0.99"}]}]}