{"data":[{"id":62962630,"name":"Aluber the Jester of Despia","type":"Effect Monster","desc":"If this card is Normal or Special Summoned: You can add 1 \"Branded\" Spell/Trap from your Deck to your hand. If a face-up Fusion Monster you control is destroyed by battle, or leaves the field because of an opponent's card effect, while this card is in your GY: You can target 1 Effect Monster your opponent controls; Special Summon this card, and if you do, negate the targeted monster's effects until the end of this turn. You can only use 1 \"Aluber the Jester of Despia\" effect per turn, and only once that turn.","atk":1800,"def":0,"level":4,"race":"Fairy","attribute":"DARK","card_sets":[{"set_name":"2022 Tin of the Pharaoh's Gods","set_code":"MP22-EN123","set_rarity":"Prismatic Secret Rare","set_rarity_code":"(PScR)","set_price":"0"},{"set_name":"Dawn of Majesty","set_code":"DAMA-EN006","set_rarity":"Secret Rare","set_rarity_code":"(ScR)","set_price":"32.68"},{"set_name":"Ghosts From the Past: The 2nd Haunting","set_code":"GFP2-EN097","set_rarity":"Ultra Rare","set_rarity_code":"(UR)","set_price":"12.24"},{"set_name":"OTS Tournament Pack 20","set_code":"OP20-EN003","set_rarity":"Ultimate Rare","set_rarity_code":"(UtR)","set_price":"0"}],"card_images":[{"id":62962630,"image_url":"https://images.ygoprodeck.com/images/cards/62962630.jpg","image_url_small":"https://images.ygoprodeck.com/images/cards_small/62962630.jpg"}],"card_prices":[{"cardmarket_price":"6.05","tcgplayer_price":"5.67","ebay_price":"5.99","amazon_price":"0.60","coolstuffinc_price":"3.99"}]}]}