{"data":[{"id":67300516,"name":"Red-Eyes Wyvern","type":"Effect Monster","desc":"During your End Phase, if you did not Normal Summon/Set a monster this turn: You can banish this card from your Graveyard; Special Summon 1 \"Red-Eyes\" monster from your Graveyard, except \"Red-Eyes B. Chick\".","atk":1800,"def":1600,"level":4,"race":"Dragon","attribute":"WIND","card_sets":[{"set_name":"Ancient Prophecy: Special Edition","set_code":"ANPR-ENSE2","set_rarity":"Super Rare","set_rarity_code":"(SR)","set_price":"7.79"},{"set_name":"Astral Pack Eight","set_code":"AP08-EN019","set_rarity":"Common","set_rarity_code":"(C)","set_price":"3.76"},{"set_name":"Legendary Collection 4: Joey's World Mega Pack","set_code":"LCJW-EN049","set_rarity":"Common","set_rarity_code":"(C)","set_price":"3.14"},{"set_name":"Legendary Duelists: Season 1","set_code":"LDS1-EN005","set_rarity":"Common","set_rarity_code":"(C)","set_price":"2.76"},{"set_name":"Rise of the True Dragons Structure Deck","set_code":"SR02-EN010","set_rarity":"Common","set_rarity_code":"(C)","set_price":"2.94"},{"set_name":"Yu-Gi-Oh! GX Tag Force 3 promotional cards","set_code":"GX06-EN002","set_rarity":"Super Rare","set_rarity_code":"(SR)","set_price":"53.57"}],"card_images":[{"id":67300516,"image_url":"https://images.ygoprodeck.com/images/cards/67300516.jpg","image_url_small":"https://images.ygoprodeck.com/images/cards_small/67300516.jpg"}],"card_prices":[{"cardmarket_price":"0.41","tcgplayer_price":"1.42","ebay_price":"4.95","amazon_price":"1.40","coolstuffinc_price":"3.99"}]}]}