{"data":[{"id":70551291,"name":"The Legendary Swordmaster Black Luster Soldier","type":"Ritual Effect Monster","desc":"You can Ritual Summon this card with \"Chaos Form\" or \"Super Soldier Ritual\". Must be Ritual Summoned. During your Draw Phase, before you draw: You can reveal this card in your hand; give up your normal draw this turn, and if you do, add 1 Ritual Spell from your Deck to your hand. Your opponent cannot activate cards or effects during your Battle Phase. When this attacking card that was Ritual Summoned using a Normal Monster destroys an opponent's monster by battle: You can shuffle all cards they control into the Deck.","atk":3000,"def":2500,"level":8,"race":"Warrior","attribute":"EARTH","card_sets":null,"card_images":[{"id":70551291,"image_url":"https://images.ygoprodeck.com/images/cards/70551291.jpg","image_url_small":"https://images.ygoprodeck.com/images/cards_small/70551291.jpg"}],"card_prices":[{"cardmarket_price":"1.65","tcgplayer_price":"0.00","ebay_price":"3.99","amazon_price":"9.49","coolstuffinc_price":"0.00"}]}]}