{"data":[{"id":71880877,"name":"Super Defense Robot Monki","type":"Effect Monster","desc":"When this card is Normal Summoned: You can Special Summon 1 \"Super Defense Robot\" monster or \"Orbital 7\" from your hand. Once per turn: You can banish 1 Machine-Type monster from your Graveyard, then target 1 \"Super Defense Robot\" monster or \"Orbital 7\" in your Graveyard; add that target to your hand.","atk":800,"def":1200,"level":3,"race":"Machine","attribute":"EARTH","card_sets":[{"set_name":"2014 Mega-Tin Mega Pack","set_code":"MP14-EN065","set_rarity":"Common","set_rarity_code":"(C)","set_price":"1.07"},{"set_name":"Judgment of the Light","set_code":"JOTL-EN008","set_rarity":"Common","set_rarity_code":"(C)","set_price":"1.21"}],"card_images":[{"id":71880877,"image_url":"https://images.ygoprodeck.com/images/cards/71880877.jpg","image_url_small":"https://images.ygoprodeck.com/images/cards_small/71880877.jpg"}],"card_prices":[{"cardmarket_price":"0.02","tcgplayer_price":"0.08","ebay_price":"2.95","amazon_price":"0.25","coolstuffinc_price":"0.49"}]}]}