{"data":[{"id":73977033,"name":"Raidraptor - Booster Strix","type":"Effect Monster","desc":"When a \"Raidraptor\" monster you control is targeted for an attack by an opponent's monster: You can banish this card from your hand; destroy the attacking monster.","atk":100,"def":1700,"level":4,"race":"Winged Beast","attribute":"DARK","card_sets":[{"set_name":"2017 Mega-Tin Mega Pack","set_code":"MP17-EN008","set_rarity":"Common","set_rarity_code":"(C)","set_price":"1.41"},{"set_name":"Shining Victories","set_code":"SHVI-EN016","set_rarity":"Common","set_rarity_code":"(C)","set_price":"1.14"}],"card_images":[{"id":73977033,"image_url":"https://images.ygoprodeck.com/images/cards/73977033.jpg","image_url_small":"https://images.ygoprodeck.com/images/cards_small/73977033.jpg"}],"card_prices":[{"cardmarket_price":"0.08","tcgplayer_price":"0.19","ebay_price":"1.00","amazon_price":"1.28","coolstuffinc_price":"0.25"}]}]}