{"data":[{"id":77783947,"name":"Yang Zing Unleashed","type":"Trap Card","desc":"All monsters your opponent controls must attack, if able. During either player's Main Phase or Battle Phase: You can send this face-up card from your Spell & Trap Zone to the Graveyard; immediately after this effect resolves, Synchro Summon 1 Synchro Monster, using 1 or more \"Yang Zing\" monsters you control as Synchro Materials.","atk":0,"def":0,"level":0,"race":"Continuous","attribute":null,"card_sets":[{"set_name":"2015 Mega-Tin Mega Pack","set_code":"MP15-EN117","set_rarity":"Common","set_rarity_code":"(C)","set_price":"1.13"},{"set_name":"Duelist Alliance","set_code":"DUEA-EN075","set_rarity":"Common","set_rarity_code":"(C)","set_price":"1.04"},{"set_name":"Duelist Alliance: Deluxe Edition","set_code":"DUEA-ENDE2","set_rarity":"Ultra Rare","set_rarity_code":"(UR)","set_price":"1.46"}],"card_images":[{"id":77783947,"image_url":"https://images.ygoprodeck.com/images/cards/77783947.jpg","image_url_small":"https://images.ygoprodeck.com/images/cards_small/77783947.jpg"}],"card_prices":[{"cardmarket_price":"0.10","tcgplayer_price":"0.10","ebay_price":"1.00","amazon_price":"0.20","coolstuffinc_price":"0.25"}]}]}