{"data":[{"id":80071763,"name":"Dark Balter the Terrible","type":"Fusion Monster","desc":"\"Possessed Dark Soul\" + \"Frontier Wiseman\"\nA Fusion Summon of this monster can only be conducted with the above Fusion Material Monsters. When a Normal Spell Card is activated, negate the effect by paying 1000 Life Points. The effect of an Effect Monster that this monster destroys as a result of battle is negated.","atk":2000,"def":1200,"level":5,"race":"Fiend","attribute":"DARK","card_sets":[{"set_name":"Dark Beginning 2","set_code":"DB2-EN125","set_rarity":"Rare","set_rarity_code":"(R)","set_price":"7.53"},{"set_name":"Hobby League 3 participation card G","set_code":"HL03-EN007","set_rarity":"Ultra Parallel Rare","set_rarity_code":"(UPR)","set_price":"15.18"},{"set_name":"Legacy of Darkness","set_code":"LOD-002","set_rarity":"Super Rare","set_rarity_code":"(SR)","set_price":"7.22"},{"set_name":"Legacy of Darkness","set_code":"LOD-EN002","set_rarity":"Super Rare","set_rarity_code":"(SR)","set_price":"0.00"},{"set_name":"Tournament Pack 6","set_code":"TP6-EN010","set_rarity":"Common","set_rarity_code":"(C)","set_price":"7.22"}],"card_images":[{"id":80071763,"image_url":"https://images.ygoprodeck.com/images/cards/80071763.jpg","image_url_small":"https://images.ygoprodeck.com/images/cards_small/80071763.jpg"}],"card_prices":[{"cardmarket_price":"5.83","tcgplayer_price":"5.13","ebay_price":"3.50","amazon_price":"5.99","coolstuffinc_price":"8.99"}]}]}