{"data":[{"id":82732705,"name":"Skill Drain","type":"Trap Card","desc":"Activate by paying 1000 LP. Negate the effects of all face-up monsters while they are face-up on the field (but their effects can still be activated).","atk":0,"def":0,"level":0,"race":"Continuous","attribute":null,"card_sets":[{"set_name":"Battle Pack: Epic Dawn","set_code":"BP01-EN053","set_rarity":"Rare","set_rarity_code":"(R)","set_price":"21.49"},{"set_name":"Battle Pack: Epic Dawn","set_code":"BP01-EN053","set_rarity":"Starfoil Rare","set_rarity_code":"(SFR)","set_price":"21.75"},{"set_name":"Dark Crisis","set_code":"DCR-049","set_rarity":"Rare","set_rarity_code":"(R)","set_price":"18.84"},{"set_name":"Dark Crisis","set_code":"DCR-EN049","set_rarity":"Rare","set_rarity_code":"(R)","set_price":"19.99"},{"set_name":"Dark Revelation Volume 1","set_code":"DR1-EN211","set_rarity":"Rare","set_rarity_code":"(R)","set_price":"21.17"},{"set_name":"Duel Terminal 3","set_code":"DT03-EN098","set_rarity":"Duel Terminal Normal Parallel Rare","set_rarity_code":"(DNPR)","set_price":"22.39"},{"set_name":"Gold Series","set_code":"GLD1-EN044","set_rarity":"Common","set_rarity_code":"(C)","set_price":"26.24"},{"set_name":"Hidden Arsenal: Chapter 1","set_code":"HAC1-EN028","set_rarity":"Common","set_rarity_code":"(C)","set_price":"0"},{"set_name":"Hidden Arsenal: Chapter 1","set_code":"HAC1-EN028","set_rarity":"Duel Terminal Ultra Parallel Rare","set_rarity_code":"(DUPR)","set_price":"20.99"},{"set_name":"Magnificent Mavens","set_code":"MAMA-EN094","set_rarity":"Ultra Rare","set_rarity_code":"(UR)","set_price":"0"},{"set_name":"OTS Tournament Pack 19","set_code":"OP19-EN003","set_rarity":"Ultimate Rare","set_rarity_code":"(UtR)","set_price":"61.25"},{"set_name":"OTS Tournament Pack 19 (POR)","set_code":"OP19-PT003","set_rarity":"Ultimate Rare","set_rarity_code":"(UtR)","set_price":"0"},{"set_name":"The Lost Art Promotion L","set_code":"LART-EN012","set_rarity":"Ultra Rare","set_rarity_code":"(UR)","set_price":"43.4"},{"set_name":"Turbo Pack: Booster Eight","set_code":"TU08-EN001","set_rarity":"Ultra Rare","set_rarity_code":"(UR)","set_price":"56.52"}],"card_images":[{"id":82732705,"image_url":"https://images.ygoprodeck.com/images/cards/82732705.jpg","image_url_small":"https://images.ygoprodeck.com/images/cards_small/82732705.jpg"}],"card_prices":[{"cardmarket_price":"5.00","tcgplayer_price":"14.56","ebay_price":"15.99","amazon_price":"29.98","coolstuffinc_price":"79.99"}]}]}