{"data":[{"id":86509711,"name":"Magicians' Combination","type":"Trap Card","desc":"Once per turn, when a card or effect is activated (except during the Damage Step): You can Tribute 1 \"Dark Magician\" or 1 \"Dark Magician Girl\"; Special Summon 1 \"Dark Magician\" or 1 \"Dark Magician Girl\" from your hand or GY, with a different name from the Tributed monster, and if you do, negate that activated effect. If this face-up card is sent from the Spell & Trap Zone to the GY: You can destroy 1 card on the field.","atk":0,"def":0,"level":0,"race":"Continuous","attribute":null,"card_sets":[{"set_name":"Legendary Duelists: Magical Hero","set_code":"LED6-EN005","set_rarity":"Ultra Rare","set_rarity_code":"(UR)","set_price":"6.1"},{"set_name":"Legendary Duelists: Season 3","set_code":"LDS3-EN099","set_rarity":"Ultra Rare","set_rarity_code":"(UR)","set_price":"2.3"}],"card_images":[{"id":86509711,"image_url":"https://images.ygoprodeck.com/images/cards/86509711.jpg","image_url_small":"https://images.ygoprodeck.com/images/cards_small/86509711.jpg"}],"card_prices":[{"cardmarket_price":"0.69","tcgplayer_price":"0.38","ebay_price":"1.30","amazon_price":"0.90","coolstuffinc_price":"3.99"}]}]}