{"data":[{"id":93211810,"name":"Sonic Boom","type":"Trap Card","desc":"During your turn: Target 1 \"Mecha Phantom Beast\" monster on the field; this turn, its ATK becomes double its original ATK, it is unaffected by other Spell/Trap effects, also if it attacks a Defense Position monster, inflict piercing battle damage to your opponent. If this effect is applied to that monster, destroy all Machine-Type monsters you control during the End Phase of this turn. Other monsters cannot attack during the turn you activate this card.","atk":0,"def":0,"level":0,"race":"Normal","attribute":null,"card_sets":[{"set_name":"2014 Mega-Tin Mega Pack","set_code":"MP14-EN109","set_rarity":"Common","set_rarity_code":"(C)","set_price":"1.08"},{"set_name":"Judgment of the Light","set_code":"JOTL-EN076","set_rarity":"Common","set_rarity_code":"(C)","set_price":"1.03"}],"card_images":[{"id":93211810,"image_url":"https://images.ygoprodeck.com/images/cards/93211810.jpg","image_url_small":"https://images.ygoprodeck.com/images/cards_small/93211810.jpg"}],"card_prices":[{"cardmarket_price":"0.04","tcgplayer_price":"0.10","ebay_price":"1.09","amazon_price":"0.25","coolstuffinc_price":"0.49"}]}]}