{"data":[{"id":93394164,"name":"Parallel Panzer","type":"Spell Card","desc":"Equip only to a Link Monster. Once per turn: You can move the equipped monster to a Main Monster Zone it points to on its controller's field. You can send this Equip Card to the GY; destroy 1 card in the same column as the monster that was equipped with this card. You can only use this effect of \"Parallel Panzer\" once per turn.","atk":0,"def":0,"level":0,"race":"Equip","attribute":null,"card_sets":[{"set_name":"2019 Gold Sarcophagus Tin Mega Pack","set_code":"MP19-EN203","set_rarity":"Common","set_rarity_code":"(C)","set_price":"1.04"},{"set_name":"Soul Fusion","set_code":"SOFU-EN066","set_rarity":"Short Print","set_rarity_code":"(SP)","set_price":"1.04"}],"card_images":[{"id":93394164,"image_url":"https://images.ygoprodeck.com/images/cards/93394164.jpg","image_url_small":"https://images.ygoprodeck.com/images/cards_small/93394164.jpg"}],"card_prices":[{"cardmarket_price":"0.05","tcgplayer_price":"0.10","ebay_price":"1.09","amazon_price":"0.45","coolstuffinc_price":"0.25"}]}]}