{"data":[{"id":94004268,"name":"Amazoness Swords Woman","type":"Effect Monster","desc":"Your opponent takes any battle damage you would have taken from battles involving this card instead.","atk":1500,"def":1600,"level":4,"race":"Warrior","attribute":"EARTH","card_sets":[{"set_name":"Dark Revelation Volume 1","set_code":"DR1-EN116","set_rarity":"Super Rare","set_rarity_code":"(SR)","set_price":"9.54"},{"set_name":"Gold Series 3","set_code":"GLD3-EN006","set_rarity":"Common","set_rarity_code":"(C)","set_price":"4.25"},{"set_name":"Legendary Duelists","set_code":"LEDU-EN013","set_rarity":"Common","set_rarity_code":"(C)","set_price":"2.48"},{"set_name":"Magician's Force","set_code":"MFC-061","set_rarity":"Ultra Rare","set_rarity_code":"(UR)","set_price":"14.31"},{"set_name":"Speed Duel Starter Decks: Duelists of Tomorrow","set_code":"SS02-ENC06","set_rarity":"Common","set_rarity_code":"(C)","set_price":"4.15"},{"set_name":"Speed Duel Tournament Pack 2","set_code":"STP2-EN004","set_rarity":"Ultra Rare","set_rarity_code":"(UR)","set_price":"51.47"},{"set_name":"Tournament Pack 7","set_code":"TP7-EN007","set_rarity":"Rare","set_rarity_code":"(R)","set_price":"7.73"}],"card_images":[{"id":94004268,"image_url":"https://images.ygoprodeck.com/images/cards/94004268.jpg","image_url_small":"https://images.ygoprodeck.com/images/cards_small/94004268.jpg"}],"card_prices":[{"cardmarket_price":"0.27","tcgplayer_price":"1.00","ebay_price":"2.95","amazon_price":"3.06","coolstuffinc_price":"4.99"}]}]}