{"data":[{"id":95286165,"name":"De-Fusion","type":"Spell Card","desc":"Target 1 Fusion Monster on the field; return that target to the Extra Deck, then, if all the Fusion Materials that were used for its Fusion Summon are in your GY, you can Special Summon all of them.","atk":0,"def":0,"level":0,"race":"Quick-Play","attribute":null,"card_sets":[{"set_name":"Dark Beginning 2","set_code":"DB2-EN029","set_rarity":"Common","set_rarity_code":"(C)","set_price":"1.86"},{"set_name":"Duel Terminal 4","set_code":"DT04-EN094","set_rarity":"Duel Terminal Normal Parallel Rare","set_rarity_code":"(DNPR)","set_price":"8.46"},{"set_name":"Duelist Pack: Zane Truesdale","set_code":"DP04-EN017","set_rarity":"Common","set_rarity_code":"(C)","set_price":"1.52"},{"set_name":"Labyrinth of Nightmare","set_code":"LON-097","set_rarity":"Super Rare","set_rarity_code":"(SR)","set_price":"6.42"},{"set_name":"Labyrinth of Nightmare","set_code":"LON-E097","set_rarity":"Super Rare","set_rarity_code":"(SR)","set_price":"60.19"},{"set_name":"Labyrinth of Nightmare","set_code":"LON-EN097","set_rarity":"Super Rare","set_rarity_code":"(SR)","set_price":"12.95"},{"set_name":"Legendary Collection 3: Yugi's World Mega Pack","set_code":"LCYW-EN063","set_rarity":"Common","set_rarity_code":"(C)","set_price":"2.28"},{"set_name":"Legendary Collection Kaiba Mega Pack","set_code":"LCKC-EN044","set_rarity":"Secret Rare","set_rarity_code":"(ScR)","set_price":"4.73"},{"set_name":"Speed Duel: Battle City Box","set_code":"SBCB-EN012","set_rarity":"Common","set_rarity_code":"(C)","set_price":"1.53"},{"set_name":"Structure Deck: Yugi Muto","set_code":"SDMY-EN032","set_rarity":"Common","set_rarity_code":"(C)","set_price":"1.35"},{"set_name":"Yugi's Legendary Decks","set_code":"YGLD-ENB31","set_rarity":"Common","set_rarity_code":"(C)","set_price":"1.54"}],"card_images":[{"id":95286165,"image_url":"https://images.ygoprodeck.com/images/cards/95286165.jpg","image_url_small":"https://images.ygoprodeck.com/images/cards_small/95286165.jpg"}],"card_prices":[{"cardmarket_price":"0.13","tcgplayer_price":"0.31","ebay_price":"9.25","amazon_price":"2.84","coolstuffinc_price":"0.79"}]}]}