{"data":[{"id":95471006,"name":"XYZ Combine","type":"Spell Card","desc":"If your LIGHT Machine Union Monster Card is banished (except during the Damage Step): You can Special Summon 1 \"X-Head Cannon\", \"Y-Dragon Head\", or \"Z-Metal Tank\" from your Deck. You can return 1 Fusion Monster you control to the Extra Deck; Special Summon up to 2 of your banished monsters with different names, from among \"X-Head Cannon\", \"Y-Dragon Head\", and \"Z-Metal Tank\". You can only use each effect of \"XYZ Combine\" once per turn.","atk":0,"def":0,"level":0,"race":"Continuous","attribute":null,"card_sets":[{"set_name":"Battle of Chaos","set_code":"BACH-EN061","set_rarity":"Super Rare","set_rarity_code":"(SR)","set_price":"1.43"}],"card_images":[{"id":95471006,"image_url":"https://images.ygoprodeck.com/images/cards/95471006.jpg","image_url_small":"https://images.ygoprodeck.com/images/cards_small/95471006.jpg"}],"card_prices":[{"cardmarket_price":"0.11","tcgplayer_price":"0.12","ebay_price":"1.25","amazon_price":"0.25","coolstuffinc_price":"0.39"}]}]}