{"data":[{"id":97173708,"name":"Oh Tokenbaum!","type":"Trap Card","desc":"Tribute 2 or more Tokens with the same Level, then target monsters in your GY with that same Level, up to the number of Tokens Tributed; Special Summon them, but their effects are negated, also destroy them during the End Phase.","atk":0,"def":0,"level":0,"race":"Normal","attribute":null,"card_sets":[{"set_name":"Shadow Specters","set_code":"SHSP-EN098","set_rarity":"Rare","set_rarity_code":"(R)","set_price":"1.09"},{"set_name":"Yu-Gi-Oh! Advent Calendar (2018)","set_code":"AC18-EN024","set_rarity":"Ultra Rare","set_rarity_code":"(UR)","set_price":"1.14"}],"card_images":[{"id":97173708,"image_url":"https://images.ygoprodeck.com/images/cards/97173708.jpg","image_url_small":"https://images.ygoprodeck.com/images/cards_small/97173708.jpg"}],"card_prices":[{"cardmarket_price":"0.09","tcgplayer_price":"0.16","ebay_price":"0.99","amazon_price":"0.20","coolstuffinc_price":"0.49"}]}]}